dga/__init__.py
dga/_gene.cpython-36m-darwin.so
dga/_gene.pyx
dga/dga.py
dga/gene.py
dga/release.py
dga/tests/test_gene.py
dga-0.1.6.dist-info/LICENSE.txt
dga-0.1.6.dist-info/METADATA
dga-0.1.6.dist-info/WHEEL
dga-0.1.6.dist-info/top_level.txt
dga-0.1.6.dist-info/RECORD
